lamarkdown/__init__.py
lamarkdown/ext/attr_prefix.py
lamarkdown/ext/captions.py
lamarkdown/ext/cite.py
lamarkdown/ext/eval.py
lamarkdown/ext/label_support/__init__.py
lamarkdown/ext/label_support/counter_types.py
lamarkdown/ext/label_support/derived_counter_types.py
lamarkdown/ext/label_support/label_renderers.py
lamarkdown/ext/label_support/label_templates.py
lamarkdown/ext/label_support/labellers.py
lamarkdown/ext/label_support/ref_resolver.py
lamarkdown/ext/label_support/standard_counter_types.py
lamarkdown/ext/labels.py
lamarkdown/ext/latex.py
lamarkdown/ext/list_tables.py
lamarkdown/ext/markdown_demo.py
lamarkdown/ext/sections.py
lamarkdown/ext/util/__init__.py
lamarkdown/ext/util/replacement_patterns.py
lamarkdown/lib/api_impl.py
lamarkdown/lib/build_params.py
lamarkdown/lib/directives.py
lamarkdown/lib/fenced_blocks.py
lamarkdown/lib/images.py
lamarkdown/lib/lamd.py
lamarkdown/lib/live.py
lamarkdown/lib/md_compiler.py
lamarkdown/lib/progress.py
lamarkdown/lib/resource_writers.py
lamarkdown/lib/resources.py
lamarkdown/mods/code.py
lamarkdown/mods/doc.py
lamarkdown/mods/page_numbers.py
lamarkdown/mods/plots.py
lamarkdown/mods/teaching.py
lamarkdown-0.10.1.dist-info/METADATA
lamarkdown-0.10.1.dist-info/WHEEL
lamarkdown-0.10.1.dist-info/entry_points.txt
lamarkdown-0.10.1.dist-info/RECORD
